{
	"jobName" : "powershell_OS_create_config_group",
	"realm" : "default",
	"clientGroup" : "default",
	"protocolType" : "ProtocolPowerShell",
	"numberOfJobThreads" : 1,
	"jobScript" : "shell_OS_create_config_group",
	"endpointQuery" : "single_powershell_with_node_details",
	"endpointIdColumn" : "ipaddress",
	"loadConfigGroups" : true,
	"updateParameters" : true,
	"isDisabled" : true,
	"runTimeValues" : {
		"maxJobRunTime" : 600,
		"maxProtocolTime" : 600,
		"maxCommandTime" : 60
	},
	"inputParameters" : {
		"printDebug" : true
	},
	"triggerType" : "interval",
	"triggerArgs" : {
		"weeks" : null,
		"days" : null,
		"hours" : null,
		"minutes" : null,
		"seconds" : 58,
		"start_date" : "",
		"end_date" : ""
	},
	"schedulerArgs" : {
		"misfire_grace_time" : 10,
		"coalesce" : 1,
		"max_instances" : 1,
		"replace_existing" : 1
	}
}
